{
  "Function element": {
    "prefix": "element",
    "body": ["${1:div}(${2:\"text\"})"],
    "description": "Create an element using Matra function syntax"
  },
  "Function element with properties": {
    "prefix": "element-props",
    "body": ["${1:div}(${2:class}=\"${3:name}\", ${4:\"text\"})"],
    "description": "Create a function-style element with a property"
  },
  "Block element": {
    "prefix": "block",
    "body": [
      "${1:div} {",
      "  $0",
      "}"
    ],
    "description": "Create an element using Matra block syntax"
  },
  "Block element with text": {
    "prefix": "block-text",
    "body": ["${1:p} { \"${2:text}\" }"] ,
    "description": "Create a block-style element with text"
  },
  "Conditional element": {
    "prefix": "m-if",
    "body": ["${1:div}[m-if=\"${2:condition}\"] {", "  $0", "}"],
    "description": "Create a conditionally rendered block element"
  },
  "Repeated element": {
    "prefix": "m-each",
    "body": ["${1:li}[m-each=\"${2:items}\" m-as=\"${3:item}\"] { \"{{${3:item}}}\" }"] ,
    "description": "Create a repeated block element"
  },
  "Interpolation": {
    "prefix": "interpolation",
    "body": ["{{${1:value}}}"],
    "description": "Insert a Matra interpolation"
  }
}
